{"name":"t:sections.footer.name","type":"footer","sections":{"footer":{"type":"footer","blocks":{"218eb584-4757-4525-a565-6fc199c842f5":{"type":"link_list","settings":{"heading":"Quick links","menu":"footer"}},"c875ba77-d23f-46f8-9244-a206f68231d5":{"type":"link_list","settings":{"heading":"Quick links","menu":"footer-menu-1"}}},"block_order":["218eb584-4757-4525-a565-6fc199c842f5","c875ba77-d23f-46f8-9244-a206f68231d5"],"settings":{"color_scheme":"scheme-9ae4ee92-afca-467a-a5bd-2c54016a2c9e","newsletter_enable":true,"newsletter_heading":"Subscribe to our emails","enable_follow_on_shop":true,"show_social":true,"enable_country_selector":true,"enable_language_selector":true,"payment_enable":true,"show_policy":false,"margin_top":0,"padding_top":36,"padding_bottom":36}}},"order":["footer"]}